async_near/__init__.py
async_near/account.py
async_near/models.py
async_near/providers.py
async_near/serializer.py
async_near/signer.py
async_near/transactions.py
async_near-1.0.1.dist-info/LICENSE
async_near-1.0.1.dist-info/METADATA
async_near-1.0.1.dist-info/WHEEL
async_near-1.0.1.dist-info/top_level.txt
async_near-1.0.1.dist-info/RECORD
