Metadata-Version: 2.1
Name: async-near
Version: 1.0.1
Summary: Near async rpc client
Home-page: https://github.com/here-wallet/async_near
Author: Petr Volnov
Author-email: petr@herewallet.app
License: MIT
Platform: UNKNOWN
License-File: LICENSE
Requires-Dist: base58
Requires-Dist: ed25519
Requires-Dist: aiohttp
